{
  "auto_generated_timesheets": "تم إنشاء {{count}} جدول زمني جديد تلقائياً للشهور الثلاثة الماضية",
  "failed_to_fetch_timesheets": "فشل في جلب الجداول الزمنية",
  "only_draft_timesheets_can_be_deleted_by_non_admin_users": "يمكن حذف الجداول الزمنية المسودة فقط من قبل المستخدمين غير الإداريين",
  "timesheet_deleted_successfully": "تم حذف الجدول الزمني بنجاح",
  "cannot_delete_timesheets_only_draft_can_be_deleted_by_non_admin_users": "لا يمكن حذف {{count}} جدول زمني - يمكن حذف الجداول الزمنية المسودة فقط من قبل المستخدمين غير الإداريين",
  "no_draft_timesheets_selected_for_deletion": "لم يتم تحديد جداول زمنية مسودة للحذف",
  "no_timesheets_selected_for_deletion": "لم يتم تحديد جداول زمنية للحذف",
  "individual_approve_functionality_to_be_implemented": "وظيفة الموافقة الفردية قيد التطوير",
  "individual_reject_functionality_to_be_implemented": "وظيفة الرفض الفردي قيد التطوير",
  "please_select_timesheets_to_process": "يرجى تحديد الجداول الزمنية للمعالجة",
  "no_pending_timesheets_found_to_process": "لم يتم العثور على جداول زمنية معلقة للمعالجة",
  "bulk_action_notes": "إجراء جماعي {{action}}",
  "all_pending_timesheets": "لجميع الجداول الزمنية المعلقة",
  "submit_for_approval": "إرسال للموافقة",
  "foreman_approval": "موافقة المشرف",
  "incharge_approval": "موافقة المسؤول",
  "checking_approval": "موافقة المراجعة",
  "manager_approval": "موافقة المدير",
  "completed": "مكتمل",
  "draft": "مسودة",
  "submitted": "مُرسل",
  "foreman_approved": "موافق عليه من المشرف",
  "incharge_approved": "موافق عليه من المسؤول",
  "checking_approved": "موافق عليه من المراجعة",
  "manager_approved": "موافق عليه من المدير",
  "rejected": "مرفوض",
  "loading_timesheets": "جاري تحميل الجداول الزمنية...",
  "timesheet_management": "إدارة الجداول الزمنية",
  "auto_generating_timesheets": "جاري إنشاء الجداول الزمنية تلقائياً...",
  "export": "تصدير",
  "sync_timesheets": "مزامنة الجداول الزمنية",
  "create_timesheet": "إنشاء جدول زمني",
  "monthly_report": "التقرير الشهري",
  "timesheet_selected": "جدول زمني محدد",
  "clear_selection": "مسح التحديد",
  "bulk_approve": "موافقة جماعية",
  "bulk_reject": "رفض جماعي",
  "bulk_delete": "حذف جماعي",
  "search_timesheets": "البحث في الجداول الزمنية...",
  "all_status": "جميع الحالات",
  "filter_by_status": "تصفية حسب الحالة",
  "filter_by_assignment": "تصفية حسب المهمة",
  "all_assignments": "جميع المهام",
  "filter_by_month": "تصفية حسب الشهر",
  "all_months": "جميع الشهور",
  "current_month": "الحالي",
  "filter_by_current_month": "تصفية حسب الشهر الحالي",
  "page_size": "حجم الصفحة",
  "5_per_page": "5 في الصفحة",
  "10_per_page": "10 في الصفحة",
  "20_per_page": "20 في الصفحة",
  "50_per_page": "50 في الصفحة",
  "timesheets": "الجداول الزمنية",
  "manage_employee_timesheets_and_approvals": "إدارة جداول الموظفين الزمنية والموافقات",
  "employee": "الموظف",
  "assignment": "المهمة",
  "date": "التاريخ",
  "hours": "الساعات",
  "status": "الحالة",
  "submitted": "مُرسل",
  "approved_by": "موافق عليه بواسطة",
  "actions": "الإجراءات",
  "no_name": "بدون اسم",
  "project": "المشروع",
  "rental": "الإيجار",
  "ot": "ساعات إضافية",
  "not_submitted": "غير مُرسل",
  "not_approved": "غير موافق عليه",
  "approve": "موافقة",
  "reject": "رفض",
  "delete_timesheet": "حذف الجدول الزمني",
  "bulk_approve_timesheets": "موافقة جماعية على الجداول الزمنية",
  "bulk_reject_timesheets": "رفض جماعي للجداول الزمنية",
  "bulk_approve_description": "الموافقة على الجداول الزمنية المحددة وفقاً لسير عمل الموافقة. سينتقل كل جدول زمني إلى مرحلة الموافقة التالية بناءً على حالته الحالية.",
  "bulk_reject_description": "رفض الجداول الزمنية المحددة. سيتم وضع علامة عليها كمرفوضة وإعادتها إلى حالة المسودة.",
  "notes_optional": "ملاحظات (اختيارية)",
  "add_any_notes_about_this_action": "أضف أي ملاحظات حول هذا الإجراء...",
  "approval_workflow": "سير عمل الموافقة",
  "current_status_next_stage": "الحالة الحالية ← المرحلة التالية",
  "required_roles": "الأدوار المطلوبة",
  "submit_draft": "إرسال المسودة",
  "foreman": "مشرف",
  "incharge": "مسؤول",
  "checking": "مراجعة",
  "manager": "مدير",
  "summary": "ملخص",
  "action": "إجراء",
  "workflow": "سير العمل",
  "following_approval_stages": "مراحل الموافقة التالية",
  "status_breakdown": "تفصيل الحالة",
  "timesheet_s": "جدول زمني",
  "notes": "ملاحظات",
  "cancel": "إلغاء",
  "processing": "جاري المعالجة",
  "all": "الكل",
  "delete_timesheet": "حذف الجدول الزمني",
  "are_you_sure_you_want_to_delete_this_timesheet": "هل أنت متأكد من حذف هذا الجدول الزمني؟ لا يمكن التراجع عن هذا الإجراء.",
  "delete_multiple_timesheets": "حذف عدة جداول زمنية",
  "are_you_sure_you_want_to_delete": "هل أنت متأكد من حذف {{count}} جدول زمني؟ لا يمكن التراجع عن هذا الإجراء.",
  "timesheets_to_be_deleted": "الجداول الزمنية المراد حذفها",
  "no_project_rental": "بدون مشروع/إيجار",
  "delete": "حذف",
  "timesheet_administration": "إدارة الجداول الزمنية",
  "advanced_timesheet_management_features_for_supervisors_and_managers": "ميزات إدارة الجداول الزمنية المتقدمة للمشرفين والمديرين",
  "approve_all_pending": "الموافقة على جميع المعلقة",
  "reject_all_pending": "رفض جميع المعلقة",
  "timesheet_settings": "إعدادات الجداول الزمنية",
  "generate_reports": "إنشاء التقارير",
  "showing_results": "عرض {{start}} إلى {{end}} من {{total}} نتيجة",
  "page": "صفحة",
  "of": "من",
  "previous": "السابق",
  "next": "التالي",
  "no_timesheets_found": "لم يتم العثور على جداول زمنية",
  "monthly_timesheet_view": "عرض الجداول الزمنية الشهرية",
  "view_and_edit_monthly_timesheets": "عرض وتعديل الجداول الزمنية الشهرية",
  "export_monthly_report": "تصدير التقرير الشهري",
  "refresh": "تحديث",
  "filter_by_employee": "تصفية حسب الموظف",
  "all_employees": "جميع الموظفين",
  "monthly_summary": "الملخص الشهري",
  "regular_hours": "الساعات العادية",
  "overtime_hours": "ساعات العمل الإضافي",
  "total_hours": "إجمالي الساعات",
  "days_worked": "أيام العمل",
  "projects_summary": "ملخص المشاريع",
  "overtime": "ساعات إضافية",
  "monthly_calendar": "التقويم الشهري",
  "automatic_approval_workflow": "سير عمل الموافقة التلقائية",
  "system_behavior": "سلوك النظام",
  "automatically_determines_next_stage": "يحدد المرحلة التالية تلقائياً",
  "moves_to_next_approval_level": "ينتقل إلى مستوى الموافقة التالي",
  "no_manual_stage_selection_needed": "لا حاجة للاختيار اليدوي للمرحلة",
  "automatic_stage_determination": "تحديد المرحلة تلقائياً",
  "employees": "الموظفون",
  "timesheet_created_successfully": "تم إنشاء الجدول الزمني بنجاح",
  "timesheet_updated_successfully": "تم تحديث الجدول الزمني بنجاح",
  "failed_to_save_timesheet": "فشل في حفظ الجدول الزمني",
  "click_to_add_timesheet": "انقر لإضافة جدول زمني",
  "click_to_edit_overtime": "انقر لتعديل ساعات العمل الإضافي",
  "edit_timesheet": "تعديل الجدول الزمني",
  "edit_timesheet_hours_and_overtime": "تعديل ساعات العمل وساعات العمل الإضافي",
  "save_changes": "حفظ التغييرات",
  "click_on_timesheet_to_edit_overtime": "انقر على الجدول الزمني لتعديل ساعات العمل الإضافي",
  "back": "رجوع"
}